word2vec/__init__.py
word2vec/_version.py
word2vec/io.py
word2vec/scripts_interface.py
word2vec/utils.py
word2vec/word2vec_noop.cpython-35m-darwin.so
word2vec/wordclusters.py
word2vec/wordvectors.py
word2vec/tests/__init__.py
word2vec/tests/test_word2vec.py
word2vec-0.9.1.data/data/bin/word2phrase
word2vec-0.9.1.data/data/bin/word2vec
word2vec-0.9.1.data/data/bin/word2vec-compute-accuracy
word2vec-0.9.1.data/data/bin/word2vec-distance
word2vec-0.9.1.data/data/bin/word2vec-doc2vec
word2vec-0.9.1.data/data/bin/word2vec-word-analogy
word2vec-0.9.1.dist-info/DESCRIPTION.rst
word2vec-0.9.1.dist-info/METADATA
word2vec-0.9.1.dist-info/RECORD
word2vec-0.9.1.dist-info/WHEEL
word2vec-0.9.1.dist-info/metadata.json
word2vec-0.9.1.dist-info/top_level.txt
