Metadata-Version: 2.0
Name: word2vec
Version: 0.9.1
Summary: Wrapper for Google word2vec
Home-page: https://github.com/danielfrg/word2vec
Author: Daniel Rodriguez
Author-email: df.rodriguez143@gmail.com
License: Apache License Version 2.0, January 2004
Platform: UNKNOWN
Requires-Dist: cython
Requires-Dist: numpy
